poetry_update/__init__.py
poetry_update/cli.py
poetry_update/core.py
poetry_update-0.1.2.dist-info/LICENSE
poetry_update-0.1.2.dist-info/METADATA
poetry_update-0.1.2.dist-info/WHEEL
poetry_update-0.1.2.dist-info/entry_points.txt
poetry_update-0.1.2.dist-info/RECORD
