Metadata-Version: 2.3
Name: poetry-update
Version: 0.1.2
Summary: A CLI tool to safely update Poetry packages to their latest versions.
License: MIT
Keywords: poetry,dependency,update,packages,automation,cli
Author: Raheel Siddiqui
Author-email: raheelsiddiqui365@gmail.com
Requires-Python: >=3.10,<4.0
Classifier: Development Status :: 4 - Beta
Classifier: Environment :: Console
Classifier: Intended Audience :: Developers
Classifier: Topic :: Software Development :: Build Tools
Classifier: Topic :: Software Development :: Libraries :: Python Modules
Classifier: License :: OSI Approved :: MIT License
Classifier: Programming Language :: Python :: 3
Classifier: Programming Language :: Python :: 3.10
Classifier: Programming Language :: Python :: 3.11
Classifier: Programming Language :: Python :: 3.12
Classifier: Programming Language :: Python :: 3.13
Requires-Dist: click (>=8.1.8,<9.0.0)
Requires-Dist: loguru (>=0.7.3,<0.8.0)
Requires-Dist: packaging (>=24.0)
Requires-Dist: toml (>=0.10.2,<0.11.0)
Project-URL: Changelog, https://github.com/rawheel/poetry-update/blob/main/CHANGELOG.md
Project-URL: Documentation, https://github.com/rawheel/poetry-update#readme
Project-URL: Homepage, https://github.com/rawheel/poetry-update
Project-URL: Repository, https://github.com/rawheel/poetry-update
